source/__init__.py
source/update.py
pip_update_all-0.1.0.dist-info/METADATA
pip_update_all-0.1.0.dist-info/WHEEL
pip_update_all-0.1.0.dist-info/entry_points.txt
pip_update_all-0.1.0.dist-info/top_level.txt
pip_update_all-0.1.0.dist-info/RECORD
